lohit/__init__.py
lohit-0.1.dist-info/LICENSE.txt
lohit-0.1.dist-info/METADATA
lohit-0.1.dist-info/WHEEL
lohit-0.1.dist-info/top_level.txt
lohit-0.1.dist-info/RECORD
