Metadata-Version: 2.1
Name: lohit
Version: 0.1
Summary: To multiply two input matrices
Author: LOHIT DHIMAN
Author-email: lohitdhiman04@gmail.com
Classifier: Programming Language :: Python :: 3
Classifier: License :: OSI Approved :: MIT License
Classifier: Operating System :: OS Independent
License-File: LICENSE.txt
